[
  {
    "Field": "id",
    "Type": "varchar(50)",
    "Null": "NO",
    "Key": "PRI",
    "Default": null,
    "Extra": ""
  },
  {
    "Field": "instrumentId",
    "Type": "varchar(50)",
    "Null": "NO",
    "Key": "MUL",
    "Default": null,
    "Extra": ""
  },
  {
    "Field": "timestamp",
    "Type": "bigint",
    "Null": "NO",
    "Key": "MUL",
    "Default": null,
    "Extra": ""
  },
  {
    "Field": "changedBy",
    "Type": "varchar(100)",
    "Null": "YES",
    "Key": "MUL",
    "Default": null,
    "Extra": ""
  },
  {
    "Field": "changeType",
    "Type": "varchar(20)",
    "Null": "NO",
    "Key": "MUL",
    "Default": null,
    "Extra": ""
  },
  {
    "Field": "fieldName",
    "Type": "varchar(50)",
    "Null": "YES",
    "Key": "",
    "Default": null,
    "Extra": ""
  },
  {
    "Field": "oldValue",
    "Type": "text",
    "Null": "YES",
    "Key": "",
    "Default": null,
    "Extra": ""
  },
  {
    "Field": "newValue",
    "Type": "text",
    "Null": "YES",
    "Key": "",
    "Default": null,
    "Extra": ""
  },
  {
    "Field": "reason",
    "Type": "text",
    "Null": "YES",
    "Key": "",
    "Default": null,
    "Extra": ""
  }
]